fruit_slots/__init__.py
fruit_slots/__main__.py
fruit_slots/fruit_slots_env.py
fruit_slots/utils.py
fruit_slots/commands/__init__.py
fruit_slots/commands/playing.py
fruit_slots/commands/plotting.py
fruit_slots/commands/training.py
fruit_slots-0.0.6.dist-info/LICENSE
fruit_slots-0.0.6.dist-info/METADATA
fruit_slots-0.0.6.dist-info/WHEEL
fruit_slots-0.0.6.dist-info/top_level.txt
fruit_slots-0.0.6.dist-info/RECORD
