Metadata-Version: 2.1
Name: fruit-slots
Version: 0.0.6
Summary: An experiment in implicit communication between learning agents
Home-page: https://github.com/cool-RR/fruit_slots
Author: Ram Rachum
Author-email: ram@rachum.com
License: UNKNOWN
Platform: UNKNOWN
Classifier: Development Status :: 3 - Alpha
Classifier: Intended Audience :: Science/Research
Classifier: Topic :: Scientific/Engineering :: Artificial Intelligence
Classifier: Programming Language :: Python :: 3.9
Classifier: Programming Language :: Python :: 3.10
Classifier: Programming Language :: Python :: 3.11
Classifier: Programming Language :: Python :: Implementation :: CPython
Classifier: License :: OSI Approved :: MIT License
Classifier: Operating System :: OS Independent
Requires-Dist: PettingZoo (==1.19.0)
Requires-Dist: SuperSuit (==3.4.0)
Requires-Dist: click (>=8.1.3)
Requires-Dist: gym (==0.22.0)
Requires-Dist: numpy (>=1.23.0)
Requires-Dist: plotly (==5.9.0)
Requires-Dist: rigged-sb3
Requires-Dist: tensorboard (==2.9.1)
Requires-Dist: tensorflow (==2.9.1)
Provides-Extra: tests
Requires-Dist: pytest ; extra == 'tests'
